ingradient-0.1.1.dist-info/licenses/LICENSE
ingradient_sdk/__init__.py
ingradient_sdk/cli.py
ingradient_sdk/utils.py
ingradient_sdk/sdk/__init__.py
ingradient_sdk/sdk/classes.py
ingradient_sdk/sdk/client.py
ingradient_sdk/sdk/datasets.py
ingradient_sdk/sdk/images.py
ingradient_sdk/sdk/model.py
ingradient_sdk/static/404.html
ingradient_sdk/static/favicon.ico
ingradient_sdk/static/file.svg
ingradient_sdk/static/globe.svg
ingradient_sdk/static/index.html
ingradient_sdk/static/index.txt
ingradient_sdk/static/next.svg
ingradient_sdk/static/vercel.svg
ingradient_sdk/static/window.svg
ingradient_sdk/static/404/index.html
ingradient_sdk/static/_next/static/bGkIbeY8w7DiiE_J8MjHS/_buildManifest.js
ingradient_sdk/static/_next/static/bGkIbeY8w7DiiE_J8MjHS/_ssgManifest.js
ingradient_sdk/static/_next/static/chunks/203.2b4c1ee4fbe3a7cf.js
ingradient_sdk/static/_next/static/chunks/218.d8ec56f1948566fd.js
ingradient_sdk/static/_next/static/chunks/219-943c0199e5009379.js
ingradient_sdk/static/_next/static/chunks/4bd1b696-e8b5b5b17c5a8136.js
ingradient_sdk/static/_next/static/chunks/517-5d32ca99e572d33e.js
ingradient_sdk/static/_next/static/chunks/520-6e3225444ab721c5.js
ingradient_sdk/static/_next/static/chunks/525-ac9e4b3b0f73e99a.js
ingradient_sdk/static/_next/static/chunks/617-5825dbeedd7255d6.js
ingradient_sdk/static/_next/static/chunks/697-8ef18dbac067e739.js
ingradient_sdk/static/_next/static/chunks/738-0736abd3532538ea.js
ingradient_sdk/static/_next/static/chunks/757-a34c0237ea007bd5.js
ingradient_sdk/static/_next/static/chunks/822-2af8fbb74f45aebb.js
ingradient_sdk/static/_next/static/chunks/870fdd6f-1dde3623bec082d1.js
ingradient_sdk/static/_next/static/chunks/921-c5a74a1d9e567e13.js
ingradient_sdk/static/_next/static/chunks/980-2d87e3202f7c2ef6.js
ingradient_sdk/static/_next/static/chunks/ca377847-b193697f4aa455cb.js
ingradient_sdk/static/_next/static/chunks/framework-881f0560c40ae817.js
ingradient_sdk/static/_next/static/chunks/main-app-d13a485b6fe555c5.js
ingradient-0.1.1.dist-info/METADATA
ingradient-0.1.1.dist-info/WHEEL
ingradient-0.1.1.dist-info/entry_points.txt
ingradient-0.1.1.dist-info/top_level.txt
ingradient-0.1.1.dist-info/RECORD
