Metadata-Version: 2.4
Name: ingradient
Version: 0.1.1
Summary: Ingradient - A labeling and dataset management tool
Author-email: JUNE LEE <june@ingradient.ai>
License-Expression: Apache-2.0
Project-URL: Homepage, https://github.com/ingradient/ingradient
Requires-Python: >=3.7
License-File: LICENSE
Requires-Dist: fastapi
Requires-Dist: uvicorn
Requires-Dist: pydantic<2.0.0
Requires-Dist: numpy<2.0.0
Requires-Dist: pillow
Requires-Dist: python-multipart
Requires-Dist: requests
Requires-Dist: sqlalchemy
Requires-Dist: onnxruntime
Requires-Dist: faiss-cpu==1.7.4
Requires-Dist: umap-learn
Dynamic: license-file
